uppercase/__init__.py
uppercase/__main__.py
file_to_uppercase-1.0.0.dist-info/LICENSE
file_to_uppercase-1.0.0.dist-info/METADATA
file_to_uppercase-1.0.0.dist-info/WHEEL
file_to_uppercase-1.0.0.dist-info/entry_points.txt
file_to_uppercase-1.0.0.dist-info/top_level.txt
file_to_uppercase-1.0.0.dist-info/RECORD
