Metadata-Version: 2.1
Name: file-to-uppercase
Version: 1.0.0
Summary: It uppercase file
Home-page: https://github.com/Saksham1904/upperacase
Author: Udit Vashisht
Author-email: sakshamgoel1901@gmail.com
License: MIT
Classifier: License :: OSI Approved :: MIT License
Classifier: Programming Language :: Python :: 3.6
Classifier: Programming Language :: Python :: 3.7
Classifier: Programming Language :: Python :: 3.8
License-File: LICENSE
